{
  "generated_at": "2026-05-09T15:41:28.616887+00:00",
  "strategies": [
    {
      "account": {
        "closed_trades": [],
        "equity": 1000.0,
        "events": [
          {
            "reasoning": "Geen breakout: volume 0.64x, RSI 54.6",
            "status": "hold"
          },
          {
            "reasoning": "Geen breakout: volume 0.64x, RSI 54.6",
            "status": "hold"
          },
          {
            "reasoning": "Geen breakout: volume 0.36x, RSI 49.6",
            "status": "hold"
          },
          {
            "reasoning": "Geen breakout: volume 0.71x, RSI 52.9",
            "status": "hold"
          },
          {
            "reasoning": "Opened virtual long because signal confidence 0.3735 met threshold. Risk budget is 1.0% of equity with explicit stop_loss and take_profit.",
            "status": "opened"
          },
          {
            "reasoning": "A virtual position is already open, so the trader will not stack exposure.",
            "status": "ignored_existing_position"
          },
          {
            "reasoning": "A virtual position is already open, so the trader will not stack exposure.",
            "status": "ignored_existing_position"
          },
          {
            "reasoning": "A virtual position is already open, so the trader will not stack exposure.",
            "status": "ignored_existing_position"
          }
        ],
        "historical_performance": {
          "average_holding_duration_seconds": 0.0,
          "daily_performance": [],
          "peak_equity": 1000.0,
          "trough_equity": 1000.0
        },
        "open_position": {
          "entry": 80588.64814,
          "opened_at": 1778340900,
          "qty": 0.03799192,
          "reasoning": "Breakout long: volume 1.27x, RSI 63.7, ATR 75.76",
          "side": "long",
          "stop_loss": 80325.43428571,
          "symbol": "BTCUSDT",
          "take_profit": 80782.19857143
        },
        "paper_trading_only": true,
        "risk_per_trade_pct": 1.0,
        "starting_cash": 1000.0
      },
      "adaptation": {
        "closed_trades": 0,
        "conclusion": "Verzamel meer data (0/30 trades). Risico beperkt tot 0.50%.",
        "drawdown_analysis": {
          "current_drawdown": 0.0,
          "current_drawdown_pct": 0.0,
          "max_drawdown": 0.0,
          "max_drawdown_pct": 0.0,
          "recovery_factor": 0.0
        },
        "expectancy": 0.0,
        "mode": "data_gathering",
        "profit_factor": 0.0,
        "regime_detection": {
          "confidence": 0.0,
          "reason": "Onvoldoende trades voor regime detection (minimaal 20 vereist)",
          "regime": "onbekend"
        },
        "rolling_windows": {
          "window_100": {
            "available": false,
            "reason": "Onvoldoende trades (0 < 100)"
          },
          "window_200": {
            "available": false,
            "reason": "Onvoldoende trades (0 < 200)"
          },
          "window_50": {
            "available": false,
            "reason": "Onvoldoende trades (0 < 50)"
          }
        },
        "statistical_significance": {
          "min_samples_needed": 30,
          "reason": "Onvoldoende samples voor statistische analyse (minimaal 30 trades vereist)",
          "significant": false
        },
        "suggested_risk_per_trade_pct": 0.5,
        "win_rate": 0.0
      },
      "decision": {
        "reasoning": "A virtual position is already open, so the trader will not stack exposure.",
        "status": "ignored_existing_position"
      },
      "signal": {
        "action": "enter_long",
        "confidence": 0.3735,
        "entry": 80588.64814,
        "entry_offset_pct": 0.001,
        "generated_at": 1778340900,
        "order_type": "limit",
        "reasoning": "Breakout long: volume 1.27x, RSI 63.7, ATR 75.76",
        "resistance": 80476.96,
        "risk_reward": 1.5,
        "stop_loss": 80325.43428571,
        "support": 80212.63,
        "symbol": "BTCUSDT",
        "take_profit": 80782.19857143,
        "timeframe": "5m",
        "volume_ratio": 1.2719
      },
      "strategy_name": "Breakout"
    },
    {
      "account": {
        "closed_trades": [],
        "equity": 1000.0,
        "events": [
          {
            "reasoning": "RSI 54.6 niet extreem genoeg (buy<25, sell>75)",
            "status": "hold"
          },
          {
            "reasoning": "RSI 54.6 niet extreem genoeg (buy<25, sell>75)",
            "status": "hold"
          },
          {
            "reasoning": "RSI 49.6 niet extreem genoeg (buy<25, sell>75)",
            "status": "hold"
          },
          {
            "reasoning": "RSI 52.9 niet extreem genoeg (buy<25, sell>75)",
            "status": "hold"
          },
          {
            "reasoning": "RSI 63.7 niet extreem genoeg (buy<25, sell>75)",
            "status": "hold"
          },
          {
            "reasoning": "RSI 63.7 niet extreem genoeg (buy<25, sell>75)",
            "status": "hold"
          },
          {
            "reasoning": "RSI 63.7 niet extreem genoeg (buy<25, sell>75)",
            "status": "hold"
          },
          {
            "reasoning": "RSI 63.7 niet extreem genoeg (buy<25, sell>75)",
            "status": "hold"
          }
        ],
        "historical_performance": {
          "average_holding_duration_seconds": 0.0,
          "daily_performance": [],
          "peak_equity": 1000.0,
          "trough_equity": 1000.0
        },
        "open_position": null,
        "paper_trading_only": true,
        "risk_per_trade_pct": 1.0,
        "starting_cash": 1000.0
      },
      "adaptation": {
        "closed_trades": 0,
        "conclusion": "Verzamel meer data (0/30 trades). Risico beperkt tot 0.50%.",
        "drawdown_analysis": {
          "current_drawdown": 0.0,
          "current_drawdown_pct": 0.0,
          "max_drawdown": 0.0,
          "max_drawdown_pct": 0.0,
          "recovery_factor": 0.0
        },
        "expectancy": 0.0,
        "mode": "data_gathering",
        "profit_factor": 0.0,
        "regime_detection": {
          "confidence": 0.0,
          "reason": "Onvoldoende trades voor regime detection (minimaal 20 vereist)",
          "regime": "onbekend"
        },
        "rolling_windows": {
          "window_100": {
            "available": false,
            "reason": "Onvoldoende trades (0 < 100)"
          },
          "window_200": {
            "available": false,
            "reason": "Onvoldoende trades (0 < 200)"
          },
          "window_50": {
            "available": false,
            "reason": "Onvoldoende trades (0 < 50)"
          }
        },
        "statistical_significance": {
          "min_samples_needed": 30,
          "reason": "Onvoldoende samples voor statistische analyse (minimaal 30 trades vereist)",
          "significant": false
        },
        "suggested_risk_per_trade_pct": 0.5,
        "win_rate": 0.0
      },
      "decision": {
        "reasoning": "RSI 63.7 niet extreem genoeg (buy<25, sell>75)",
        "status": "hold"
      },
      "signal": {
        "action": "hold",
        "confidence": 0.0,
        "entry": 80508.14,
        "entry_offset_pct": 0.001,
        "generated_at": 1778340900,
        "order_type": "limit",
        "reasoning": "RSI 63.7 niet extreem genoeg (buy<25, sell>75)",
        "resistance": 0.0,
        "risk_reward": 0.0,
        "stop_loss": 0.0,
        "support": 0.0,
        "symbol": "BTCUSDT",
        "take_profit": 0.0,
        "timeframe": "5m",
        "volume_ratio": 0.0
      },
      "strategy_name": "Mean Reversion"
    },
    {
      "account": {
        "closed_trades": [],
        "equity": 1000.0,
        "events": [
          {
            "reasoning": "Geen conservatief setup: volume 0.64x, RSI 54.6",
            "status": "hold"
          },
          {
            "reasoning": "Geen conservatief setup: volume 0.64x, RSI 54.6",
            "status": "hold"
          },
          {
            "reasoning": "Geen conservatief setup: volume 0.36x, RSI 49.6",
            "status": "hold"
          },
          {
            "reasoning": "Geen conservatief setup: volume 0.73x, RSI 52.9",
            "status": "hold"
          },
          {
            "reasoning": "Opened virtual long because signal confidence 0.6792 met threshold. Risk budget is 1.0% of equity with explicit stop_loss and take_profit.",
            "status": "opened"
          },
          {
            "reasoning": "A virtual position is already open, so the trader will not stack exposure.",
            "status": "ignored_existing_position"
          },
          {
            "reasoning": "A virtual position is already open, so the trader will not stack exposure.",
            "status": "ignored_existing_position"
          },
          {
            "reasoning": "A virtual position is already open, so the trader will not stack exposure.",
            "status": "ignored_existing_position"
          }
        ],
        "historical_performance": {
          "average_holding_duration_seconds": 0.0,
          "daily_performance": [],
          "peak_equity": 1000.0,
          "trough_equity": 1000.0
        },
        "open_position": {
          "entry": 80588.64814,
          "opened_at": 1778340900,
          "qty": 0.05334728,
          "reasoning": "Conservatief long: volume 1.34x, RSI 63.7, confidence 0.68",
          "side": "long",
          "stop_loss": 80401.19714286,
          "symbol": "BTCUSDT",
          "take_profit": 80722.02571429
        },
        "paper_trading_only": true,
        "risk_per_trade_pct": 1.0,
        "starting_cash": 1000.0
      },
      "adaptation": {
        "closed_trades": 0,
        "conclusion": "Verzamel meer data (0/30 trades). Risico beperkt tot 0.50%.",
        "drawdown_analysis": {
          "current_drawdown": 0.0,
          "current_drawdown_pct": 0.0,
          "max_drawdown": 0.0,
          "max_drawdown_pct": 0.0,
          "recovery_factor": 0.0
        },
        "expectancy": 0.0,
        "mode": "data_gathering",
        "profit_factor": 0.0,
        "regime_detection": {
          "confidence": 0.0,
          "reason": "Onvoldoende trades voor regime detection (minimaal 20 vereist)",
          "regime": "onbekend"
        },
        "rolling_windows": {
          "window_100": {
            "available": false,
            "reason": "Onvoldoende trades (0 < 100)"
          },
          "window_200": {
            "available": false,
            "reason": "Onvoldoende trades (0 < 200)"
          },
          "window_50": {
            "available": false,
            "reason": "Onvoldoende trades (0 < 50)"
          }
        },
        "statistical_significance": {
          "min_samples_needed": 30,
          "reason": "Onvoldoende samples voor statistische analyse (minimaal 30 trades vereist)",
          "significant": false
        },
        "suggested_risk_per_trade_pct": 0.5,
        "win_rate": 0.0
      },
      "decision": {
        "reasoning": "A virtual position is already open, so the trader will not stack exposure.",
        "status": "ignored_existing_position"
      },
      "signal": {
        "action": "enter_long",
        "confidence": 0.6792,
        "entry": 80588.64814,
        "entry_offset_pct": 0.001,
        "generated_at": 1778340900,
        "order_type": "limit",
        "reasoning": "Conservatief long: volume 1.34x, RSI 63.7, confidence 0.68",
        "resistance": 80476.96,
        "risk_reward": 2.0,
        "stop_loss": 80401.19714286,
        "support": 80212.63,
        "symbol": "BTCUSDT",
        "take_profit": 80722.02571429,
        "timeframe": "5m",
        "volume_ratio": 1.3356
      },
      "strategy_name": "Conservative"
    },
    {
      "account": {
        "closed_trades": [],
        "equity": 1000.0,
        "events": [
          {
            "reasoning": "Geen breakout: volume 0.64x, RSI 54.6",
            "status": "hold"
          },
          {
            "reasoning": "Geen breakout: volume 0.64x, RSI 54.6",
            "status": "hold"
          },
          {
            "reasoning": "Geen breakout: volume 0.36x, RSI 49.6",
            "status": "hold"
          },
          {
            "reasoning": "Geen breakout: volume 0.71x, RSI 52.9",
            "status": "hold"
          },
          {
            "reasoning": "Opened virtual long because signal confidence 0.3735 met threshold. Risk budget is 1.0% of equity with explicit stop_loss and take_profit.",
            "status": "opened"
          },
          {
            "reasoning": "A virtual position is already open, so the trader will not stack exposure.",
            "status": "ignored_existing_position"
          },
          {
            "reasoning": "A virtual position is already open, so the trader will not stack exposure.",
            "status": "ignored_existing_position"
          },
          {
            "reasoning": "A virtual position is already open, so the trader will not stack exposure.",
            "status": "ignored_existing_position"
          }
        ],
        "historical_performance": {
          "average_holding_duration_seconds": 0.0,
          "daily_performance": [],
          "peak_equity": 1000.0,
          "trough_equity": 1000.0
        },
        "open_position": {
          "entry": 80588.64814,
          "opened_at": 1778340900,
          "qty": 0.03799192,
          "reasoning": "Breakout long: volume 1.27x, RSI 63.7, ATR 75.76",
          "side": "long",
          "stop_loss": 80325.43428571,
          "symbol": "BTCUSDT",
          "take_profit": 80782.19857143
        },
        "paper_trading_only": true,
        "risk_per_trade_pct": 1.0,
        "starting_cash": 1000.0
      },
      "adaptation": {
        "closed_trades": 0,
        "conclusion": "Verzamel meer data (0/30 trades). Risico beperkt tot 0.50%.",
        "drawdown_analysis": {
          "current_drawdown": 0.0,
          "current_drawdown_pct": 0.0,
          "max_drawdown": 0.0,
          "max_drawdown_pct": 0.0,
          "recovery_factor": 0.0
        },
        "expectancy": 0.0,
        "mode": "data_gathering",
        "profit_factor": 0.0,
        "regime_detection": {
          "confidence": 0.0,
          "reason": "Onvoldoende trades voor regime detection (minimaal 20 vereist)",
          "regime": "onbekend"
        },
        "rolling_windows": {
          "window_100": {
            "available": false,
            "reason": "Onvoldoende trades (0 < 100)"
          },
          "window_200": {
            "available": false,
            "reason": "Onvoldoende trades (0 < 200)"
          },
          "window_50": {
            "available": false,
            "reason": "Onvoldoende trades (0 < 50)"
          }
        },
        "statistical_significance": {
          "min_samples_needed": 30,
          "reason": "Onvoldoende samples voor statistische analyse (minimaal 30 trades vereist)",
          "significant": false
        },
        "suggested_risk_per_trade_pct": 0.5,
        "win_rate": 0.0
      },
      "decision": {
        "reasoning": "A virtual position is already open, so the trader will not stack exposure.",
        "status": "ignored_existing_position"
      },
      "signal": {
        "action": "enter_long",
        "confidence": 0.3735,
        "entry": 80588.64814,
        "entry_offset_pct": 0.001,
        "generated_at": 1778340900,
        "order_type": "limit",
        "reasoning": "Breakout long: volume 1.27x, RSI 63.7, ATR 75.76",
        "resistance": 80476.96,
        "risk_reward": 1.5,
        "stop_loss": 80325.43428571,
        "support": 80212.63,
        "symbol": "BTCUSDT",
        "take_profit": 80782.19857143,
        "timeframe": "5m",
        "volume_ratio": 1.2719
      },
      "strategy_name": "Martingale"
    }
  ],
  "total_accounts": 4
}
