{
  "generated_at": "2026-05-09T13:10:47.101251+00:00",
  "strategies": [
    {
      "account": {
        "closed_trades": [],
        "equity": 1000.0,
        "events": [
          {
            "reasoning": "Geen breakout: volume 0.64x, RSI 54.6",
            "status": "hold"
          },
          {
            "reasoning": "Geen breakout: volume 0.64x, RSI 54.6",
            "status": "hold"
          }
        ],
        "historical_performance": {
          "average_holding_duration_seconds": 0.0,
          "daily_performance": [],
          "peak_equity": 1000.0,
          "trough_equity": 1000.0
        },
        "open_position": null,
        "paper_trading_only": true,
        "risk_per_trade_pct": 1.0,
        "starting_cash": 1000.0
      },
      "adaptation": {
        "closed_trades": 0,
        "conclusion": "Verzamel meer data (0/30 trades). Risico beperkt tot 0.50%.",
        "drawdown_analysis": {
          "current_drawdown": 0.0,
          "current_drawdown_pct": 0.0,
          "max_drawdown": 0.0,
          "max_drawdown_pct": 0.0,
          "recovery_factor": 0.0
        },
        "expectancy": 0.0,
        "mode": "data_gathering",
        "profit_factor": 0.0,
        "regime_detection": {
          "confidence": 0.0,
          "reason": "Onvoldoende trades voor regime detection (minimaal 20 vereist)",
          "regime": "onbekend"
        },
        "rolling_windows": {
          "window_100": {
            "available": false,
            "reason": "Onvoldoende trades (0 < 100)"
          },
          "window_200": {
            "available": false,
            "reason": "Onvoldoende trades (0 < 200)"
          },
          "window_50": {
            "available": false,
            "reason": "Onvoldoende trades (0 < 50)"
          }
        },
        "statistical_significance": {
          "min_samples_needed": 30,
          "reason": "Onvoldoende samples voor statistische analyse (minimaal 30 trades vereist)",
          "significant": false
        },
        "suggested_risk_per_trade_pct": 0.5,
        "win_rate": 0.0
      },
      "decision": {
        "reasoning": "Geen breakout: volume 0.64x, RSI 54.6",
        "status": "hold"
      },
      "signal": {
        "action": "hold",
        "confidence": 0.0,
        "entry": 80412.47,
        "entry_offset_pct": 0.001,
        "generated_at": 1778331900,
        "order_type": "limit",
        "reasoning": "Geen breakout: volume 0.64x, RSI 54.6",
        "resistance": 0.0,
        "risk_reward": 0.0,
        "stop_loss": 0.0,
        "support": 0.0,
        "symbol": "BTCUSDT",
        "take_profit": 0.0,
        "timeframe": "5m",
        "volume_ratio": 0.0
      },
      "strategy_name": "Breakout"
    },
    {
      "account": {
        "closed_trades": [],
        "equity": 1000.0,
        "events": [
          {
            "reasoning": "RSI 54.6 niet extreem genoeg (buy<25, sell>75)",
            "status": "hold"
          },
          {
            "reasoning": "RSI 54.6 niet extreem genoeg (buy<25, sell>75)",
            "status": "hold"
          }
        ],
        "historical_performance": {
          "average_holding_duration_seconds": 0.0,
          "daily_performance": [],
          "peak_equity": 1000.0,
          "trough_equity": 1000.0
        },
        "open_position": null,
        "paper_trading_only": true,
        "risk_per_trade_pct": 1.0,
        "starting_cash": 1000.0
      },
      "adaptation": {
        "closed_trades": 0,
        "conclusion": "Verzamel meer data (0/30 trades). Risico beperkt tot 0.50%.",
        "drawdown_analysis": {
          "current_drawdown": 0.0,
          "current_drawdown_pct": 0.0,
          "max_drawdown": 0.0,
          "max_drawdown_pct": 0.0,
          "recovery_factor": 0.0
        },
        "expectancy": 0.0,
        "mode": "data_gathering",
        "profit_factor": 0.0,
        "regime_detection": {
          "confidence": 0.0,
          "reason": "Onvoldoende trades voor regime detection (minimaal 20 vereist)",
          "regime": "onbekend"
        },
        "rolling_windows": {
          "window_100": {
            "available": false,
            "reason": "Onvoldoende trades (0 < 100)"
          },
          "window_200": {
            "available": false,
            "reason": "Onvoldoende trades (0 < 200)"
          },
          "window_50": {
            "available": false,
            "reason": "Onvoldoende trades (0 < 50)"
          }
        },
        "statistical_significance": {
          "min_samples_needed": 30,
          "reason": "Onvoldoende samples voor statistische analyse (minimaal 30 trades vereist)",
          "significant": false
        },
        "suggested_risk_per_trade_pct": 0.5,
        "win_rate": 0.0
      },
      "decision": {
        "reasoning": "RSI 54.6 niet extreem genoeg (buy<25, sell>75)",
        "status": "hold"
      },
      "signal": {
        "action": "hold",
        "confidence": 0.0,
        "entry": 80412.47,
        "entry_offset_pct": 0.001,
        "generated_at": 1778331900,
        "order_type": "limit",
        "reasoning": "RSI 54.6 niet extreem genoeg (buy<25, sell>75)",
        "resistance": 0.0,
        "risk_reward": 0.0,
        "stop_loss": 0.0,
        "support": 0.0,
        "symbol": "BTCUSDT",
        "take_profit": 0.0,
        "timeframe": "5m",
        "volume_ratio": 0.0
      },
      "strategy_name": "Mean Reversion"
    },
    {
      "account": {
        "closed_trades": [],
        "equity": 1000.0,
        "events": [
          {
            "reasoning": "Geen conservatief setup: volume 0.64x, RSI 54.6",
            "status": "hold"
          },
          {
            "reasoning": "Geen conservatief setup: volume 0.64x, RSI 54.6",
            "status": "hold"
          }
        ],
        "historical_performance": {
          "average_holding_duration_seconds": 0.0,
          "daily_performance": [],
          "peak_equity": 1000.0,
          "trough_equity": 1000.0
        },
        "open_position": null,
        "paper_trading_only": true,
        "risk_per_trade_pct": 1.0,
        "starting_cash": 1000.0
      },
      "adaptation": {
        "closed_trades": 0,
        "conclusion": "Verzamel meer data (0/30 trades). Risico beperkt tot 0.50%.",
        "drawdown_analysis": {
          "current_drawdown": 0.0,
          "current_drawdown_pct": 0.0,
          "max_drawdown": 0.0,
          "max_drawdown_pct": 0.0,
          "recovery_factor": 0.0
        },
        "expectancy": 0.0,
        "mode": "data_gathering",
        "profit_factor": 0.0,
        "regime_detection": {
          "confidence": 0.0,
          "reason": "Onvoldoende trades voor regime detection (minimaal 20 vereist)",
          "regime": "onbekend"
        },
        "rolling_windows": {
          "window_100": {
            "available": false,
            "reason": "Onvoldoende trades (0 < 100)"
          },
          "window_200": {
            "available": false,
            "reason": "Onvoldoende trades (0 < 200)"
          },
          "window_50": {
            "available": false,
            "reason": "Onvoldoende trades (0 < 50)"
          }
        },
        "statistical_significance": {
          "min_samples_needed": 30,
          "reason": "Onvoldoende samples voor statistische analyse (minimaal 30 trades vereist)",
          "significant": false
        },
        "suggested_risk_per_trade_pct": 0.5,
        "win_rate": 0.0
      },
      "decision": {
        "reasoning": "Geen conservatief setup: volume 0.64x, RSI 54.6",
        "status": "hold"
      },
      "signal": {
        "action": "hold",
        "confidence": 0.0,
        "entry": 80412.47,
        "entry_offset_pct": 0.001,
        "generated_at": 1778331900,
        "order_type": "limit",
        "reasoning": "Geen conservatief setup: volume 0.64x, RSI 54.6",
        "resistance": 0.0,
        "risk_reward": 0.0,
        "stop_loss": 0.0,
        "support": 0.0,
        "symbol": "BTCUSDT",
        "take_profit": 0.0,
        "timeframe": "5m",
        "volume_ratio": 0.0
      },
      "strategy_name": "Conservative"
    },
    {
      "account": {
        "closed_trades": [],
        "equity": 1000.0,
        "events": [
          {
            "reasoning": "Geen breakout: volume 0.64x, RSI 54.6",
            "status": "hold"
          },
          {
            "reasoning": "Geen breakout: volume 0.64x, RSI 54.6",
            "status": "hold"
          }
        ],
        "historical_performance": {
          "average_holding_duration_seconds": 0.0,
          "daily_performance": [],
          "peak_equity": 1000.0,
          "trough_equity": 1000.0
        },
        "open_position": null,
        "paper_trading_only": true,
        "risk_per_trade_pct": 1.0,
        "starting_cash": 1000.0
      },
      "adaptation": {
        "closed_trades": 0,
        "conclusion": "Verzamel meer data (0/30 trades). Risico beperkt tot 0.50%.",
        "drawdown_analysis": {
          "current_drawdown": 0.0,
          "current_drawdown_pct": 0.0,
          "max_drawdown": 0.0,
          "max_drawdown_pct": 0.0,
          "recovery_factor": 0.0
        },
        "expectancy": 0.0,
        "mode": "data_gathering",
        "profit_factor": 0.0,
        "regime_detection": {
          "confidence": 0.0,
          "reason": "Onvoldoende trades voor regime detection (minimaal 20 vereist)",
          "regime": "onbekend"
        },
        "rolling_windows": {
          "window_100": {
            "available": false,
            "reason": "Onvoldoende trades (0 < 100)"
          },
          "window_200": {
            "available": false,
            "reason": "Onvoldoende trades (0 < 200)"
          },
          "window_50": {
            "available": false,
            "reason": "Onvoldoende trades (0 < 50)"
          }
        },
        "statistical_significance": {
          "min_samples_needed": 30,
          "reason": "Onvoldoende samples voor statistische analyse (minimaal 30 trades vereist)",
          "significant": false
        },
        "suggested_risk_per_trade_pct": 0.5,
        "win_rate": 0.0
      },
      "decision": {
        "reasoning": "Geen breakout: volume 0.64x, RSI 54.6",
        "status": "hold"
      },
      "signal": {
        "action": "hold",
        "confidence": 0.0,
        "entry": 80412.47,
        "entry_offset_pct": 0.001,
        "generated_at": 1778331900,
        "order_type": "limit",
        "reasoning": "Geen breakout: volume 0.64x, RSI 54.6",
        "resistance": 0.0,
        "risk_reward": 0.0,
        "stop_loss": 0.0,
        "support": 0.0,
        "symbol": "BTCUSDT",
        "take_profit": 0.0,
        "timeframe": "5m",
        "volume_ratio": 0.0
      },
      "strategy_name": "Martingale"
    }
  ],
  "total_accounts": 4
}
